{
  "malId": "71",
  "audio": "dub",
  "episodes": {
    "1": {
      "op": {
        "start": 0.19,
        "end": 90.52,
        "auto": true,
        "conf": 0.9
      },
      "ed": {
        "start": 1255.43,
        "end": 1345.95,
        "auto": true,
        "permissive": true,
        "conf": 0.4
      }
    },
    "2": {
      "op": {
        "start": 0,
        "end": 90.33,
        "auto": true,
        "conf": 0.9
      }
    },
    "3": {
      "op": {
        "start": 0,
        "end": 90.15,
        "auto": true,
        "conf": 0.9
      },
      "ed": {
        "start": 1255.08,
        "end": 1345.6,
        "auto": true,
        "conf": 0.9
      }
    },
    "4": {
      "op": {
        "start": 0,
        "end": 90.89,
        "auto": true,
        "conf": 0.9
      },
      "ed": {
        "start": 1255.99,
        "end": 1345.58,
        "auto": true,
        "conf": 0.9
      }
    },
    "5": {
      "op": {
        "start": 0,
        "end": 90.89,
        "auto": true,
        "conf": 0.9
      },
      "ed": {
        "start": 1255.32,
        "end": 1345.46,
        "auto": true,
        "conf": 0.9
      }
    },
    "6": {
      "op": {
        "start": 0,
        "end": 90.33,
        "auto": true,
        "conf": 0.9
      },
      "ed": {
        "start": 1254.83,
        "end": 1344.98,
        "auto": true,
        "permissive": true,
        "conf": 0.4
      }
    },
    "7": {
      "op": {
        "start": 0,
        "end": 90.33,
        "auto": true,
        "conf": 0.9
      },
      "ed": {
        "start": 1254.94,
        "end": 1344.72,
        "auto": true,
        "conf": 0.9
      }
    },
    "8": {
      "op": {
        "start": 7.06,
        "end": 95.94,
        "auto": true,
        "conf": 0.9
      },
      "ed": {
        "start": 1195.2,
        "end": 1284.23,
        "auto": true,
        "conf": 0.9
      }
    },
    "9": {
      "op": {
        "start": 0,
        "end": 90.71,
        "auto": true,
        "conf": 0.9
      },
      "ed": {
        "start": 1255.13,
        "end": 1344.53,
        "auto": true,
        "conf": 0.9
      }
    },
    "10": {
      "op": {
        "start": 0,
        "end": 90.52,
        "auto": true,
        "conf": 0.9
      },
      "ed": {
        "start": 1255.36,
        "end": 1345.51,
        "auto": true,
        "conf": 0.9
      }
    },
    "11": {
      "op": {
        "start": 0,
        "end": 90.71,
        "auto": true,
        "conf": 0.9
      },
      "ed": {
        "start": 1254.94,
        "end": 1345.09,
        "auto": true,
        "conf": 0.9
      }
    },
    "12": {
      "op": {
        "start": 0,
        "end": 91.26,
        "auto": true,
        "conf": 0.9
      },
      "ed": {
        "start": 1254.94,
        "end": 1344.35,
        "auto": true,
        "permissive": true,
        "conf": 0.4
      }
    },
    "13": {
      "op": {
        "start": 0,
        "end": 90.71,
        "auto": true,
        "conf": 0.9
      },
      "ed": {
        "start": 1254.94,
        "end": 1344.35,
        "auto": true,
        "permissive": true,
        "conf": 0.4
      }
    },
    "14": {
      "op": {
        "start": 0,
        "end": 90.52,
        "auto": true,
        "conf": 0.9
      },
      "ed": {
        "start": 1263.72,
        "end": 1344.34,
        "auto": true,
        "permissive": true,
        "conf": 0.5
      }
    },
    "15": {
      "op": {
        "start": 0,
        "end": 90.52,
        "auto": true,
        "conf": 0.9
      },
      "ed": {
        "start": 1253.43,
        "end": 1342.1,
        "auto": true,
        "conf": 0.9
      }
    },
    "16": {
      "op": {
        "start": 0.37,
        "end": 90.89,
        "auto": true,
        "conf": 0.9
      },
      "ed": {
        "start": 1254.22,
        "end": 1341.74,
        "auto": true,
        "conf": 0.9
      }
    },
    "17": {
      "op": {
        "start": 0,
        "end": 90.33,
        "auto": true,
        "conf": 0.9
      },
      "ed": {
        "start": 1257.22,
        "end": 1347.32,
        "auto": true,
        "conf": 0.85
      }
    },
    "18": {
      "op": {
        "start": 0,
        "end": 90.33,
        "auto": true,
        "conf": 0.9
      },
      "ed": {
        "start": 1254.55,
        "end": 1345.25,
        "auto": true,
        "conf": 0.9
      }
    },
    "19": {
      "op": {
        "start": 0.19,
        "end": 90.71,
        "auto": true,
        "conf": 0.9
      },
      "ed": {
        "start": 1255.66,
        "end": 1345.44,
        "auto": true,
        "conf": 0.9
      }
    },
    "20": {
      "op": {
        "start": 0.19,
        "end": 90.34,
        "auto": true,
        "permissive": true,
        "conf": 0.65
      },
      "ed": {
        "start": 1255.32,
        "end": 1345.09,
        "auto": true,
        "conf": 0.9
      }
    },
    "21": {
      "op": {
        "start": 0,
        "end": 90.52,
        "auto": true,
        "permissive": true,
        "conf": 0.65
      },
      "ed": {
        "start": 1254.57,
        "end": 1343.98,
        "auto": true,
        "permissive": true,
        "conf": 0.4
      }
    },
    "22": {
      "op": {
        "start": 0,
        "end": 89.96,
        "auto": true,
        "conf": 0.9
      },
      "ed": {
        "start": 1254.53,
        "end": 1343.93,
        "auto": true,
        "permissive": true,
        "conf": 0.4
      }
    },
    "23": {
      "op": {
        "start": 0,
        "end": 90.15,
        "auto": true,
        "permissive": true,
        "conf": 0.65
      },
      "ed": {
        "start": 1254.53,
        "end": 1343.93,
        "auto": true,
        "permissive": true,
        "conf": 0.4
      }
    },
    "24": {}
  }
}